chat/__init__.py
chat/admin.py
chat/apps.py
chat/consumers.py
chat/models.py
chat/routing.py
chat/tests.py
chat/urls.py
chat/views.py
chat/migrations/0001_initial.py
chat/migrations/__init__.py
chat/static/chat/styles.css
chat/templates/chat/base.html
chat/templates/chat/chat.html
chat/templates/chat/login.html
chat/templates/chat/messages.html
django_proj_chat-0.1.1.dist-info/licenses/LICENSE
django_proj_chat-0.1.1.dist-info/METADATA
django_proj_chat-0.1.1.dist-info/WHEEL
django_proj_chat-0.1.1.dist-info/top_level.txt
django_proj_chat-0.1.1.dist-info/RECORD
