Metadata-Version: 2.4
Name: django-proj-chat
Version: 0.1.1
Summary: A reusable Django app for real-time instant messaging
Home-page: https://github.com/cangeorgecode/django_im
Author: George
Author-email: georgedjangodev@gmail.com
Classifier: Framework :: Django
Classifier: Programming Language :: Python :: 3
Classifier: License :: OSI Approved :: MIT License
License-File: LICENSE
Requires-Dist: Django>=5.0
Requires-Dist: channels>=4.0
Requires-Dist: channels-redis>=4.0
Requires-Dist: daphne>=4.0
Dynamic: author
Dynamic: author-email
Dynamic: classifier
Dynamic: home-page
Dynamic: license-file
Dynamic: requires-dist
Dynamic: summary
